{
  "source": "openmeteo",
  "captured_at": "2026-05-04T12:02:08.266554-04:00",
  "location": "Boone",
  "forecast_for": "2026-05-04",
  "current": {
    "temp_f": 60.0,
    "feels_like_f": 56.4,
    "humidity": 39,
    "wind_mph": 9.6,
    "weather_code": 0,
    "conditions": "Clear sky"
  },
  "daily": [
    {
      "date": "2026-05-04",
      "high_f": 69.6,
      "low_f": 41.1,
      "precip_in": 0.0,
      "snow_in": 0.0,
      "precip_prob": 3,
      "weather_code": 1,
      "conditions": "Mainly clear",
      "category": "clear",
      "wind_mph": 11.9
    },
    {
      "date": "2026-05-05",
      "high_f": 69.4,
      "low_f": 51.1,
      "precip_in": 0.0,
      "snow_in": 0.0,
      "precip_prob": 10,
      "weather_code": 3,
      "conditions": "Overcast",
      "category": "cloudy",
      "wind_mph": 14.1
    },
    {
      "date": "2026-05-06",
      "high_f": 64.8,
      "low_f": 52.9,
      "precip_in": 0.745,
      "snow_in": 0.0,
      "precip_prob": 84,
      "weather_code": 81,
      "conditions": "Moderate rain showers",
      "category": "rain",
      "wind_mph": 9.8
    },
    {
      "date": "2026-05-07",
      "high_f": 64.8,
      "low_f": 35.1,
      "precip_in": 0.274,
      "snow_in": 0.022,
      "precip_prob": 88,
      "weather_code": 71,
      "conditions": "Slight snow",
      "category": "snow",
      "wind_mph": 16.5
    },
    {
      "date": "2026-05-08",
      "high_f": 63.7,
      "low_f": 32.2,
      "precip_in": 0.0,
      "snow_in": 0.0,
      "precip_prob": 29,
      "weather_code": 3,
      "conditions": "Overcast",
      "category": "cloudy",
      "wind_mph": 12.0
    },
    {
      "date": "2026-05-09",
      "high_f": 58.6,
      "low_f": 41.4,
      "precip_in": 0.0,
      "snow_in": 0.0,
      "precip_prob": 22,
      "weather_code": 3,
      "conditions": "Overcast",
      "category": "cloudy",
      "wind_mph": 9.4
    },
    {
      "date": "2026-05-10",
      "high_f": 57.7,
      "low_f": 49.9,
      "precip_in": 0.012,
      "snow_in": 0.0,
      "precip_prob": 18,
      "weather_code": 51,
      "conditions": "Light drizzle",
      "category": "drizzle",
      "wind_mph": 4.8
    }
  ]
}