{
  "source": "openmeteo",
  "label": "Open-Meteo",
  "captured_at": "2026-07-19T00:42:05.210167-04:00",
  "location": "North Wilkesboro",
  "location_slug": "north-wilkesboro",
  "daily": [
    {
      "date": "2026-07-19",
      "high_f": 92.8,
      "low_f": 71.4,
      "wind_mph": 12.5,
      "precip_type": "none",
      "rain_in": 0,
      "snow_in": 0.0,
      "precip_in": 0.0,
      "weather_code": 3,
      "conditions": "Overcast",
      "category": "cloudy",
      "fields_provided": [
        "high",
        "low",
        "wind",
        "precip_type",
        "rain_amount",
        "snow_amount"
      ]
    },
    {
      "date": "2026-07-20",
      "high_f": 88.8,
      "low_f": 74.2,
      "wind_mph": 7.9,
      "precip_type": "none",
      "rain_in": 0,
      "snow_in": 0.0,
      "precip_in": 0.0,
      "weather_code": 3,
      "conditions": "Overcast",
      "category": "cloudy",
      "fields_provided": [
        "high",
        "low",
        "wind",
        "precip_type",
        "rain_amount",
        "snow_amount"
      ]
    },
    {
      "date": "2026-07-21",
      "high_f": 96.9,
      "low_f": 70.1,
      "wind_mph": 16.8,
      "precip_type": "rain",
      "rain_in": 0.268,
      "snow_in": 0.0,
      "precip_in": 0.268,
      "weather_code": 81,
      "conditions": "Moderate rain showers",
      "category": "rain",
      "fields_provided": [
        "high",
        "low",
        "wind",
        "precip_type",
        "rain_amount",
        "snow_amount"
      ]
    },
    {
      "date": "2026-07-22",
      "high_f": 93.1,
      "low_f": 70.3,
      "wind_mph": 12.6,
      "precip_type": "rain",
      "rain_in": 0.252,
      "snow_in": 0.0,
      "precip_in": 0.252,
      "weather_code": 95,
      "conditions": "Thunderstorm",
      "category": "storm",
      "fields_provided": [
        "high",
        "low",
        "wind",
        "precip_type",
        "rain_amount",
        "snow_amount"
      ]
    },
    {
      "date": "2026-07-23",
      "high_f": 90.1,
      "low_f": 64.5,
      "wind_mph": 5.3,
      "precip_type": "none",
      "rain_in": 0,
      "snow_in": 0.0,
      "precip_in": 0.0,
      "weather_code": 3,
      "conditions": "Overcast",
      "category": "cloudy",
      "fields_provided": [
        "high",
        "low",
        "wind",
        "precip_type",
        "rain_amount",
        "snow_amount"
      ]
    },
    {
      "date": "2026-07-24",
      "high_f": 89.2,
      "low_f": 62.3,
      "wind_mph": 4.8,
      "precip_type": "none",
      "rain_in": 0,
      "snow_in": 0.0,
      "precip_in": 0.0,
      "weather_code": 3,
      "conditions": "Overcast",
      "category": "cloudy",
      "fields_provided": [
        "high",
        "low",
        "wind",
        "precip_type",
        "rain_amount",
        "snow_amount"
      ]
    },
    {
      "date": "2026-07-25",
      "high_f": 70.6,
      "low_f": 65.0,
      "wind_mph": 2.7,
      "precip_type": "rain",
      "rain_in": 0.012,
      "snow_in": 0.0,
      "precip_in": 0.012,
      "weather_code": 51,
      "conditions": "Light drizzle",
      "category": "drizzle",
      "fields_provided": [
        "high",
        "low",
        "wind",
        "precip_type",
        "rain_amount",
        "snow_amount"
      ]
    }
  ]
}