{
  "date": "2026-07-21",
  "captured_at": "2026-07-21T07:47:16.922860-04:00",
  "source": "Open-Meteo (same as live widget)",
  "location": "Boone, NC",
  "current": {
    "temp_f": 69.9,
    "feels_like_f": 72.9,
    "wind": "SW @ 6 mph",
    "wind_dir": "SW",
    "wind_mph": 6.0,
    "gust_mph": 14.8,
    "humidity_pct": 84.0,
    "conditions": "Overcast"
  },
  "forecast": {
    "today_high_f": 80.3,
    "tonight_low_f": 67.3,
    "day_low_f": 67.3,
    "wind_mph": 14.7,
    "precip_in": 0.004,
    "snow_in": 0.0,
    "conditions": "Light drizzle",
    "category": "drizzle"
  },
  "daily": [
    {
      "date": "2026-07-21",
      "high_f": 80.3,
      "low_f": 67.3,
      "wind_mph": 14.7,
      "precip_in": 0.004,
      "snow_in": 0.0,
      "conditions": "Light drizzle",
      "category": "drizzle"
    },
    {
      "date": "2026-07-22",
      "high_f": 75.1,
      "low_f": 67.9,
      "wind_mph": 13.7,
      "precip_in": 0.984,
      "snow_in": 0.0,
      "conditions": "Moderate rain showers",
      "category": "rain"
    },
    {
      "date": "2026-07-23",
      "high_f": 66.5,
      "low_f": 62.8,
      "wind_mph": 5.9,
      "precip_in": 0.214,
      "snow_in": 0.0,
      "conditions": "Slight rain showers",
      "category": "rain"
    }
  ],
  "error": null
}