{
  "source": "openmeteo",
  "captured_at": "2026-03-16T07:50:31.639739-04:00",
  "location": "Boone",
  "forecast_for": "2026-03-16",
  "current": {
    "temp_f": 52.8,
    "feels_like_f": 48.0,
    "humidity": 90,
    "wind_mph": 11.5,
    "weather_code": 3,
    "conditions": "Overcast"
  },
  "daily": [
    {
      "date": "2026-03-16",
      "high_f": 55.3,
      "low_f": 18.0,
      "precip_in": 1.397,
      "precip_prob": 85,
      "weather_code": 75,
      "conditions": "Heavy snow",
      "category": "snow",
      "wind_mph": 29.3
    },
    {
      "date": "2026-03-17",
      "high_f": 23.9,
      "low_f": 14.5,
      "precip_in": 0.268,
      "precip_prob": 15,
      "weather_code": 75,
      "conditions": "Heavy snow",
      "category": "snow",
      "wind_mph": 31.2
    },
    {
      "date": "2026-03-18",
      "high_f": 36.9,
      "low_f": 15.0,
      "precip_in": 0.004,
      "precip_prob": 3,
      "weather_code": 51,
      "conditions": "Light drizzle",
      "category": "drizzle",
      "wind_mph": 8.4
    },
    {
      "date": "2026-03-19",
      "high_f": 49.6,
      "low_f": 31.1,
      "precip_in": 0.0,
      "precip_prob": 8,
      "weather_code": 3,
      "conditions": "Overcast",
      "category": "cloudy",
      "wind_mph": 9.4
    },
    {
      "date": "2026-03-20",
      "high_f": 59.9,
      "low_f": 35.2,
      "precip_in": 0.0,
      "precip_prob": 4,
      "weather_code": 3,
      "conditions": "Overcast",
      "category": "cloudy",
      "wind_mph": 8.4
    },
    {
      "date": "2026-03-21",
      "high_f": 62.8,
      "low_f": 51.4,
      "precip_in": 0.055,
      "precip_prob": 7,
      "weather_code": 51,
      "conditions": "Light drizzle",
      "category": "drizzle",
      "wind_mph": 11.5
    },
    {
      "date": "2026-03-22",
      "high_f": 66.6,
      "low_f": 51.3,
      "precip_in": 0.0,
      "precip_prob": 10,
      "weather_code": 3,
      "conditions": "Overcast",
      "category": "cloudy",
      "wind_mph": 17.4
    }
  ]
}