{
  "source": "openweathermap",
  "label": "OpenWeatherMap",
  "captured_at": "2026-06-29T12:52:18.339867-04:00",
  "location": "Boone",
  "daily": [
    {
      "date": "2026-06-29",
      "high_f": 80.4,
      "low_f": 77.1,
      "wind_mph": 6.5,
      "precip_type": "none",
      "rain_in": null,
      "snow_in": null,
      "fields_provided": [
        "high",
        "low",
        "wind",
        "precip_type",
        "rain_amount"
      ]
    },
    {
      "date": "2026-06-30",
      "high_f": 78.8,
      "low_f": 62.8,
      "wind_mph": 4.8,
      "precip_type": "rain",
      "rain_in": 0.072,
      "snow_in": null,
      "fields_provided": [
        "high",
        "low",
        "wind",
        "precip_type",
        "rain_amount"
      ]
    },
    {
      "date": "2026-07-01",
      "high_f": 90.7,
      "low_f": 64.7,
      "wind_mph": 7,
      "precip_type": "rain",
      "rain_in": 0.173,
      "snow_in": null,
      "fields_provided": [
        "high",
        "low",
        "wind",
        "precip_type",
        "rain_amount"
      ]
    },
    {
      "date": "2026-07-02",
      "high_f": 89.6,
      "low_f": 65.3,
      "wind_mph": 9.5,
      "precip_type": "rain",
      "rain_in": 0.109,
      "snow_in": null,
      "fields_provided": [
        "high",
        "low",
        "wind",
        "precip_type",
        "rain_amount"
      ]
    },
    {
      "date": "2026-07-03",
      "high_f": 88.9,
      "low_f": 66.7,
      "wind_mph": 7.8,
      "precip_type": "none",
      "rain_in": null,
      "snow_in": null,
      "fields_provided": [
        "high",
        "low",
        "wind",
        "precip_type",
        "rain_amount"
      ]
    },
    {
      "date": "2026-07-04",
      "high_f": 85.7,
      "low_f": 67.3,
      "wind_mph": 3.0,
      "precip_type": "none",
      "rain_in": null,
      "snow_in": null,
      "fields_provided": [
        "high",
        "low",
        "wind",
        "precip_type",
        "rain_amount"
      ]
    }
  ]
}