{
  "source": "raysweather",
  "label": "Ray's Weather",
  "captured_at": "2026-07-21T07:47:38.931297-04:00",
  "location": "Bakersville",
  "location_slug": "bakersville",
  "rays_station_id": "36",
  "rays_station_name": "Bakersville",
  "daily": [
    {
      "date": "2026-07-21",
      "high_f": 87,
      "low_f": 67,
      "golfballs": 3,
      "fields_provided": [
        "high",
        "low"
      ]
    },
    {
      "date": "2026-07-22",
      "high_f": 79,
      "low_f": 65,
      "golfballs": 2,
      "fields_provided": [
        "high",
        "low"
      ]
    },
    {
      "date": "2026-07-23",
      "high_f": 77,
      "low_f": 61,
      "golfballs": 3,
      "fields_provided": [
        "high",
        "low"
      ]
    },
    {
      "date": "2026-07-24",
      "high_f": 75,
      "low_f": 62,
      "golfballs": 3,
      "fields_provided": [
        "high",
        "low"
      ]
    },
    {
      "date": "2026-07-25",
      "high_f": 77,
      "low_f": 63,
      "golfballs": 2,
      "fields_provided": [
        "high",
        "low"
      ]
    },
    {
      "date": "2026-07-26",
      "high_f": 80,
      "low_f": 62,
      "golfballs": 4,
      "fields_provided": [
        "high",
        "low"
      ]
    },
    {
      "date": "2026-07-27",
      "high_f": 84,
      "low_f": 63,
      "golfballs": 5,
      "fields_provided": [
        "high",
        "low"
      ]
    }
  ]
}