{
  "source": "openmeteo",
  "captured_at": "2026-04-30T11:46:55.773532-04:00",
  "location": "Boone",
  "forecast_for": "2026-04-30",
  "current": {
    "temp_f": 53.8,
    "feels_like_f": 49.5,
    "humidity": 75,
    "wind_mph": 12.6,
    "weather_code": 1,
    "conditions": "Mainly clear"
  },
  "daily": [
    {
      "date": "2026-04-30",
      "high_f": 58.8,
      "low_f": 46.1,
      "precip_in": 0.0,
      "snow_in": 0.0,
      "precip_prob": 2,
      "weather_code": 3,
      "conditions": "Overcast",
      "category": "cloudy",
      "wind_mph": 16.1
    },
    {
      "date": "2026-05-01",
      "high_f": 61.2,
      "low_f": 39.1,
      "precip_in": 0.0,
      "snow_in": 0.0,
      "precip_prob": 14,
      "weather_code": 3,
      "conditions": "Overcast",
      "category": "cloudy",
      "wind_mph": 14.3
    },
    {
      "date": "2026-05-02",
      "high_f": 53.6,
      "low_f": 38.3,
      "precip_in": 0.032,
      "snow_in": 0.0,
      "precip_prob": 52,
      "weather_code": 55,
      "conditions": "Dense drizzle",
      "category": "drizzle",
      "wind_mph": 13.6
    },
    {
      "date": "2026-05-03",
      "high_f": 57.0,
      "low_f": 31.3,
      "precip_in": 0.0,
      "snow_in": 0.0,
      "precip_prob": 20,
      "weather_code": 0,
      "conditions": "Clear sky",
      "category": "clear",
      "wind_mph": 10.8
    },
    {
      "date": "2026-05-04",
      "high_f": 68.9,
      "low_f": 40.8,
      "precip_in": 0.0,
      "snow_in": 0.0,
      "precip_prob": 6,
      "weather_code": 3,
      "conditions": "Overcast",
      "category": "cloudy",
      "wind_mph": 8.6
    },
    {
      "date": "2026-05-05",
      "high_f": 64.8,
      "low_f": 45.3,
      "precip_in": 0.012,
      "snow_in": 0.0,
      "precip_prob": 14,
      "weather_code": 51,
      "conditions": "Light drizzle",
      "category": "drizzle",
      "wind_mph": 6.6
    },
    {
      "date": "2026-05-06",
      "high_f": 63.0,
      "low_f": 49.4,
      "precip_in": 0.083,
      "snow_in": 0.0,
      "precip_prob": 59,
      "weather_code": 51,
      "conditions": "Light drizzle",
      "category": "drizzle",
      "wind_mph": 7.1
    }
  ]
}