{
  "date": "2025-12-16",
  "generated_at": "2026-06-23T12:43:57.159445-04:00",
  "actuals": {
    "date": "2025-12-16",
    "location": "Boone",
    "high_f": 48.6,
    "low_f": 26.0,
    "wind_mph": 13.3,
    "gust_mph": 33.6,
    "rain_in": 0,
    "snow_in": 0.0,
    "precip_type": "none",
    "precip_in": 0.0,
    "weather_code": 1,
    "conditions": "Mainly clear",
    "category": "clear"
  },
  "sweater_weather": {
    "answer": "YES",
    "detail": "Still sweater territory. Don't let anyone tell you otherwise.",
    "layers": "1-2 (light to medium sweater)",
    "emoji": "\ud83e\uddf6\ud83d\udc4d",
    "sweater_count": 3
  },
  "sources": {
    "openmeteo": {
      "prediction": {
        "date": "2025-12-16",
        "high_f": 47.5,
        "low_f": 28.6,
        "wind_mph": 27.2,
        "precip_type": "none",
        "rain_in": 0,
        "snow_in": 0.0,
        "precip_in": 0.0,
        "precip_prob": 0,
        "weather_code": 45,
        "conditions": "Fog",
        "category": "fog",
        "fields_provided": [
          "high",
          "low",
          "wind",
          "precip_type",
          "rain_amount",
          "snow_amount"
        ]
      },
      "score": {
        "score": 78.2,
        "grade": {
          "verdict": "right",
          "ray_count": 4
        },
        "coverage": {
          "high_temp": true,
          "low_temp": true,
          "wind": true,
          "precip_type": true,
          "precip_amount": true
        },
        "breakdown": {
          "high_temp": {
            "points": 30.0,
            "max": 30,
            "scored": true,
            "predicted": 47.5,
            "actual": 48.6,
            "error": 1.1
          },
          "low_temp": {
            "points": 28.2,
            "max": 30,
            "scored": true,
            "predicted": 28.6,
            "actual": 26.0,
            "error": 2.6
          },
          "wind": {
            "points": 0.0,
            "max": 20,
            "scored": true,
            "predicted": 27.2,
            "actual": 13.3,
            "error": 13.9
          },
          "precip_type": {
            "points": 10.0,
            "max": 10,
            "scored": true,
            "predicted": "none",
            "actual": "none"
          },
          "precip_amount": {
            "points": 10.0,
            "max": 10,
            "scored": true,
            "predicted": 0,
            "actual": 0.0,
            "error": 0.0,
            "unit": "in_liquid"
          }
        },
        "raw_points": 78.2,
        "max_available": 100
      }
    }
  }
}