{
  "date": "2026-03-19",
  "generated_at": "2026-06-22T20:54:15.988141-04:00",
  "actuals": {
    "date": "2026-03-19",
    "fetched_at": "2026-03-20T11:10:45.344926-04:00",
    "location": "Boone",
    "high_f": 52.2,
    "low_f": 24.6,
    "precip_in": 0.0,
    "snow_in": 0.0,
    "wind_mph": 8.3,
    "gust_mph": 20.1,
    "weather_code": 3,
    "conditions": "Overcast",
    "category": "cloudy"
  },
  "sweater_weather": {
    "answer": "YES",
    "detail": "Still sweater territory. Don't let anyone tell you otherwise.",
    "layers": "1-2 (light to medium sweater)",
    "emoji": "\ud83e\uddf6\ud83d\udc4d",
    "sweater_count": 3
  },
  "sources": {
    "openmeteo": {
      "prediction": {
        "date": "2026-03-19",
        "high_f": 52.6,
        "low_f": 32.5,
        "precip_in": 0.0,
        "snow_in": 0.0,
        "precip_prob": 1,
        "weather_code": 45,
        "conditions": "Fog",
        "category": "fog",
        "wind_mph": 14.3
      },
      "score": {
        "score": 76.3,
        "grade": {
          "verdict": "right",
          "ray_count": 4
        },
        "coverage": {
          "high_temp": true,
          "low_temp": true,
          "wind": true,
          "precip_type": true,
          "precip_amount": true
        },
        "breakdown": {
          "high_temp": {
            "points": 30.0,
            "max": 30,
            "scored": true
          },
          "low_temp": {
            "points": 12.3,
            "max": 30,
            "scored": true
          },
          "wind": {
            "points": 14.0,
            "max": 20,
            "scored": true
          },
          "precip_type": {
            "points": 10.0,
            "max": 10,
            "scored": true
          },
          "precip_amount": {
            "points": 10.0,
            "max": 10,
            "scored": true
          }
        }
      }
    },
    "raysweather": {
      "prediction": {
        "today_high_f": 56.0,
        "tonight_low_f": 36.0,
        "category": "unknown",
        "daytime_desc": "Mostly to partly cloudy; Closer to seasonal temperatures; Light NW wind"
      },
      "score": {
        "score": 36.4,
        "grade": {
          "verdict": "wrong",
          "ray_count": 1
        },
        "coverage": {
          "high_temp": true,
          "low_temp": true,
          "wind": false,
          "precip_type": true,
          "precip_amount": false
        },
        "breakdown": {
          "high_temp": {
            "points": 24.6,
            "max": 30,
            "scored": true
          },
          "low_temp": {
            "points": 1.8,
            "max": 30,
            "scored": true
          },
          "wind": {
            "points": null,
            "max": 20,
            "scored": false
          },
          "precip_type": {
            "points": 10.0,
            "max": 10,
            "scored": true
          },
          "precip_amount": {
            "points": null,
            "max": 10,
            "scored": false
          }
        }
      }
    },
    "apple_weather": {
      "prediction": {
        "today_high_f": 52.6,
        "tonight_low_f": 32.5,
        "day_low_f": 32.5,
        "wind_mph": 14.3,
        "precip_in": 0.0,
        "snow_in": 0.0,
        "conditions": "Fog",
        "category": "fog",
        "source": "Open-Meteo (iPhone fallback)"
      },
      "score": {
        "score": 76.3,
        "grade": {
          "verdict": "right",
          "ray_count": 4
        },
        "coverage": {
          "high_temp": true,
          "low_temp": true,
          "wind": true,
          "precip_type": true,
          "precip_amount": true
        },
        "breakdown": {
          "high_temp": {
            "points": 30.0,
            "max": 30,
            "scored": true
          },
          "low_temp": {
            "points": 12.3,
            "max": 30,
            "scored": true
          },
          "wind": {
            "points": 14.0,
            "max": 20,
            "scored": true
          },
          "precip_type": {
            "points": 10.0,
            "max": 10,
            "scored": true
          },
          "precip_amount": {
            "points": 10.0,
            "max": 10,
            "scored": true
          }
        }
      }
    }
  },
  "rays_current": {
    "temp_f": 42.9,
    "feels_like_f": null,
    "wind": null,
    "wind_dir": null,
    "wind_mph": null,
    "gust_mph": null,
    "humidity_pct": null,
    "rainfall_in": null
  }
}