{
  "date": "2026-05-09",
  "generated_at": "2026-06-24T12:44:54.799187-04:00",
  "actuals": {
    "date": "2026-05-09",
    "fetched_at": "2026-05-10T11:30:39.226250-04:00",
    "location": "Boone",
    "high_f": 66.2,
    "low_f": 45.2,
    "precip_in": 0.0,
    "snow_in": 0.0,
    "wind_mph": 11.8,
    "gust_mph": 29.3,
    "weather_code": 3,
    "conditions": "Overcast",
    "category": "cloudy"
  },
  "sweater_weather": {
    "answer": "NO",
    "detail": "No sweater needed unless you're in aggressive AC.",
    "layers": "0 (the sweater rests today)",
    "emoji": "\u2600\ufe0f\u274c",
    "sweater_count": 1
  },
  "sources": {
    "openmeteo": {
      "prediction": {
        "date": "2026-05-09",
        "high_f": 67.6,
        "low_f": 43.6,
        "precip_in": 0.0,
        "snow_in": 0.0,
        "precip_prob": 1,
        "weather_code": 3,
        "conditions": "Overcast",
        "category": "cloudy",
        "wind_mph": 15.9
      },
      "score": {
        "score": 97.8,
        "grade": {
          "verdict": "right",
          "ray_count": 5
        },
        "coverage": {
          "high_temp": true,
          "low_temp": true,
          "wind": true,
          "precip_type": true,
          "precip_amount": true
        },
        "breakdown": {
          "high_temp": {
            "points": 30.0,
            "max": 30,
            "scored": true,
            "predicted": 67.6,
            "actual": 66.2,
            "error": 1.4
          },
          "low_temp": {
            "points": 30.0,
            "max": 30,
            "scored": true,
            "predicted": 43.6,
            "actual": 45.2,
            "error": 1.6
          },
          "wind": {
            "points": 17.8,
            "max": 20,
            "scored": true,
            "predicted": 15.9,
            "actual": 11.8,
            "error": 4.1
          },
          "precip_type": {
            "points": 10.0,
            "max": 10,
            "scored": true,
            "predicted": "none",
            "actual": "none"
          },
          "precip_amount": {
            "points": 10.0,
            "max": 10,
            "scored": true,
            "predicted": 0.0,
            "actual": 0.0,
            "error": 0.0,
            "unit": "in_liquid"
          }
        }
      }
    },
    "raysweather": {
      "prediction": {
        "today_high_f": 69.0,
        "tonight_low_f": 47.0,
        "category": "unknown",
        "daytime_desc": "Partly sunny with a milder afternoon; Light SW wind becoming NW 5-10 mph",
        "wind_mph": 7.5,
        "wind_lo": 5,
        "wind_hi": 10,
        "precip_type": "none"
      },
      "score": {
        "score": 90.0,
        "grade": {
          "verdict": "right",
          "ray_count": 5
        },
        "coverage": {
          "high_temp": true,
          "low_temp": true,
          "wind": true,
          "precip_type": true,
          "precip_amount": true
        },
        "breakdown": {
          "high_temp": {
            "points": 27.6,
            "max": 30,
            "scored": true,
            "predicted": 69.0,
            "actual": 66.2,
            "error": 2.8
          },
          "low_temp": {
            "points": 30.0,
            "max": 30,
            "scored": true,
            "predicted": 47.0,
            "actual": 45.2,
            "error": 1.8
          },
          "wind": {
            "points": 12.4,
            "max": 20,
            "scored": true,
            "predicted": "5-10",
            "actual": 11.8,
            "error": 4.3
          },
          "precip_type": {
            "points": 10.0,
            "max": 10,
            "scored": true,
            "predicted": "none",
            "actual": "none"
          },
          "precip_amount": {
            "points": 10.0,
            "max": 10,
            "scored": true,
            "predicted": 0.0,
            "actual": 0.0,
            "error": 0.0,
            "unit": "in_liquid"
          }
        }
      }
    },
    "apple_weather": {
      "prediction": {
        "today_high_f": 67.6,
        "tonight_low_f": 43.6,
        "day_low_f": 43.6,
        "wind_mph": 15.9,
        "precip_in": 0.0,
        "snow_in": 0.0,
        "conditions": "Overcast",
        "category": "cloudy",
        "source": "Open-Meteo (iPhone fallback)"
      },
      "score": {
        "score": 97.8,
        "grade": {
          "verdict": "right",
          "ray_count": 5
        },
        "coverage": {
          "high_temp": true,
          "low_temp": true,
          "wind": true,
          "precip_type": true,
          "precip_amount": true
        },
        "breakdown": {
          "high_temp": {
            "points": 30.0,
            "max": 30,
            "scored": true,
            "predicted": 67.6,
            "actual": 66.2,
            "error": 1.4
          },
          "low_temp": {
            "points": 30.0,
            "max": 30,
            "scored": true,
            "predicted": 43.6,
            "actual": 45.2,
            "error": 1.6
          },
          "wind": {
            "points": 17.8,
            "max": 20,
            "scored": true,
            "predicted": 15.9,
            "actual": 11.8,
            "error": 4.1
          },
          "precip_type": {
            "points": 10.0,
            "max": 10,
            "scored": true,
            "predicted": "none",
            "actual": "none"
          },
          "precip_amount": {
            "points": 10.0,
            "max": 10,
            "scored": true,
            "predicted": 0.0,
            "actual": 0.0,
            "error": 0.0,
            "unit": "in_liquid"
          }
        }
      }
    }
  },
  "rays_current": {
    "temp_f": 61.1,
    "feels_like_f": null,
    "wind": null,
    "wind_dir": null,
    "wind_mph": null,
    "gust_mph": null,
    "humidity_pct": null,
    "rainfall_in": null
  }
}