{
  "date": "2026-06-21",
  "captured_at": "2026-06-21T11:50:00.571957-04:00",
  "url": "https://raysweather.com/Forecast/Boone",
  "current": {
    "temp_f": 76.2,
    "feels_like_f": null,
    "wind": null,
    "wind_dir": null,
    "wind_mph": null,
    "gust_mph": null,
    "humidity_pct": null,
    "rainfall_in": null
  },
  "forecast": {
    "today_high_f": 82.0,
    "tonight_low_f": 62.0,
    "raw_strip": [
      [
        "hi",
        82.0
      ],
      [
        "lo",
        62.0
      ],
      [
        "hi",
        79.0
      ],
      [
        "lo",
        62.0
      ],
      [
        "hi",
        76.0
      ],
      [
        "lo",
        56.0
      ],
      [
        "hi",
        78.0
      ],
      [
        "lo",
        57.0
      ],
      [
        "hi",
        78.0
      ],
      [
        "lo",
        60.0
      ]
    ]
  },
  "narrative": "Temperatures take a step up today, and dads will enjoy quite a bit of sunshine, mixed with some afternoon cloudiness, for this Father's Day + first day of summer combo. Despite the very warm temperatures and lots of sunshine, we will remain well shy of record highs, and humidity levels should be quite comfortable. This quiet stretch of weather gives way to our next shot at meaningful rain Monday afternoon.\n\n2027 Blue Ridge Calendar Pre-Publication Sale is Underway!\n\nThe 2027 Blue Ridge Calendar is being printed now and will be available around July 1. Until then, the Pre-Publication Sale is underway with the best price we will offer all year. Get your 2027 calendars at 26% off when you buy 2 or more. As in previous years, we have scheduled special Pickup times around NW NC to save you the cost of shipping. Click here for pickup times and locations.\n\nYou can see all the winning photography at our Photo Contest page .\n\nGet the free RWC Mobile App...: Apple and Android\n\nHi: 82",
  "raw_text": "Show map\nBoone\nRight Now\n76.2\u00b0F\nToday's forecast: Sunshine, mixed with some clouds in the afternoon; Warmer for Dad; Wind becoming SW 5-10 mph. High 82\u00b0\nStation sponsor\nForecast\nCurrent\nGraphics\nArchives\nWebcams\n\nFine Father's Day\n\nLast Updated Sun June 21 at 9:37AM by Alan Simmons\n\nTemperatures take a step up today, and dads will enjoy quite a bit of sunshine, mixed with some afternoon cloudiness, for this Father's Day + first day of summer combo. Despite the very warm temperatures and lots of sunshine, we will remain well shy of record highs, and humidity levels should be quite comfortable. This quiet stretch of weather gives way to our next shot at meaningful rain Monday afternoon.\n\n2027 Blue Ridge Calendar Pre-Publication Sale is Underway!\n\nThe 2027 Blue Ridge Calendar is being printed now and will be available around July 1. Until then, the Pre-Publication Sale is underway with the best price we will offer all year. Get your 2027 calendars at 26% off when you buy 2 or more. As in previous years, we have scheduled special Pickup times around NW NC to save you the cost of shipping. Click here for pickup times and locations.\n\nYou can see all the winning photography at our Photo Contest page .\n\nGet the free RWC Mobile App...: Apple and Android\n\nHi: 82\nSunday\nSunshine, mixed with some clouds in the afternoon; Warmer for Dad; Wind becoming SW 5-10 mph\nLo: 62\nSunday night\nPartly cloudy; Mild; Light SW wind\nHi: 79\nMonday\nTurning mostly cloudy; Still warm & more humid; Afternoon showers & thunderstorms roll in; WSW wind 5-15 mph\nLo: 62\nMonday night\nMostly cloudy; Evening showers & storms diminish overnight; SW wind 5-10 mph becoming WNW 5-15\nHi: 76\nTuesday\nWidely scattered showers especially along the western escarpment; Otherwise becoming partly sunny; Comfortable; NW wind 5-15 mph\nLo: 56\nTuesday night\nBecoming mainly clear; Seasonable temps; Light NW wind\nHi: 78\nWednesday\nMostly sunny; Very nice\nLo: 57\nWednesday night\nScattered clouds; Pleasant\nHi: 78\nThursday\nPartly sunny; Hit-or-miss afternoon showers & thundershowers\nLo: 60\nThursday night\nMaybe an early shower or thundershower; Partly cloudy\nFriday\n\nExtended forecast is only available for RaysWeather.com supporters.\nSubscribe\n\nSaturday\n\nExtended forecast is only available for RaysWeather.com supporters.\nSubscribe\n\nForecast Discussion\n\nNice weather sticks around for one more day, giving us a great finish to the holiday weekend. A hardly noticeable warm front will push back north through the area today and that will give us a boost in temperatures and some clouds to go along with the sunshine this afternoon.\n\nClouds and humidity increase tonight ahead of our next summertime cool front. The front brings us rainfall in the form of showers and thunderstorms, which should arrive Monday afternoon and last well into the evening. Rainfall amounts overall don't look tremendous with this next front, but it will help the ongoing drought situation, and we could see a couple of spots wind up with some decent totals. A few showers linger into Tuesday behind the front, mostly along the western escarpment, but these are nothing to write home about and will fade away during the day.\n\nWeak high pressure builds back in for a nicer day Wednesday. This being late June, you know we can't hold dry, stable air off for long. Increasing moisture surges back into the area on Thursday as stubborn high pressure sets up shop over the western Atlantic. This leads to a daily scattering of mostly afternoon and evening showers or thundershowers each day Thursday through Saturday.\n\nDetailed forecast discussion and analysis is only available to RaysWeather supporters.\n\nSubscribe\nLog in\nAlan Simmons\nPHOTO OF THE DAY\nCLICK TO ENLARGE\nDon\u2019t worry! Just needs to dry off! Submitted by Rebecca McCandless.\nAll Photos\nSubmit Photo\nLatest Insights\nWWR? Wolf Laurel!\n\n<video controls src=\"https://d3efbyumrgw1ny.cloudfront.net/Jun-18-2026-1781795436_0780511.MOV\" width=\"400\"></video>\n\nJun 18, 2026\nYadkin Valley Deluge\n\nA morning complex of thunderstorms moving across the Ohio Valley and into West Virginia and Virginia produced an outflow boundary that pushed southward into North Carolina during the afternoon of June 18. This outflow boundary, the result of a cool rush of air from thunderstorms occurring to the north, served as an effective focusing mechanism for training thunderstorms that occurred over parts of Surry, northern Wilkes and southern Alleghany County during Thursday afternoon and evening.\n\nThis occurred under the backdrop of increasing tropical moisture returning from the southwest as the remnants of Tropical Storm Arthur moved into Alabama.\n\nThe result was excessive rainfall, in the range of 2-4 inches, with locally higher amounts of around 5 inches in central Surry County.\n\nJun 19, 2026\nMonday Message for June 15, 2026\n\nIt's the pre-summer solstice edition of the Monday Message, available for subscribers. El Ni\u00f1o has officially arrived, and will have significant implications for our weather heading into fall and winter.\n\nJun 15, 2026\nSee all\nGolf-O-Meter\n0 Golfballs\n\tOnly ducks or polar bears.\n\n\tGood day for knitting.\n\n\tMaybe, if you are brave.\n\n\tWorth taking a chance.\n\n\tA good day to be outside.\n\n\tBosses, you'd better stand at the door. (Or will bosses be first out the door?)\nCONTACT US\nPrivacy Policy\nTerms and Conditions\nContact Us",
  "daily": [
    {
      "date": "2026-06-21",
      "day_name": "Sunday",
      "high_f": 82.0,
      "low_f": 62.0,
      "wind_mph": 7.5,
      "wind_lo": 5,
      "wind_hi": 10,
      "precip_type": "none",
      "daytime_desc": "Sunshine, mixed with some clouds in the afternoon; Warmer for Dad; Wind becoming SW 5-10 mph",
      "overnight_desc": "Partly cloudy; Mild; Light SW wind",
      "category": "unknown",
      "precip_in": null
    },
    {
      "date": "2026-06-22",
      "day_name": "Monday",
      "high_f": 79.0,
      "low_f": 62.0,
      "wind_mph": 10.0,
      "wind_lo": 5,
      "wind_hi": 15,
      "precip_type": "rain",
      "daytime_desc": "Turning mostly cloudy; Still warm & more humid; Afternoon showers & thunderstorms roll in; WSW wind 5-15 mph",
      "overnight_desc": "Mostly cloudy; Evening showers & storms diminish overnight; SW wind 5-10 mph becoming WNW 5-15",
      "category": "unknown",
      "precip_in": null
    },
    {
      "date": "2026-06-23",
      "day_name": "Tuesday",
      "high_f": 76.0,
      "low_f": 56.0,
      "wind_mph": 10.0,
      "wind_lo": 5,
      "wind_hi": 15,
      "precip_type": "rain",
      "daytime_desc": "Widely scattered showers especially along the western escarpment; Otherwise becoming partly sunny; Comfortable; NW wind 5-15 mph",
      "overnight_desc": "Becoming mainly clear; Seasonable temps; Light NW wind",
      "category": "unknown",
      "precip_in": null
    },
    {
      "date": "2026-06-24",
      "day_name": "Wednesday",
      "high_f": 78.0,
      "low_f": 57.0,
      "wind_mph": null,
      "wind_lo": null,
      "wind_hi": null,
      "precip_type": "none",
      "daytime_desc": "Mostly sunny; Very nice",
      "overnight_desc": "Scattered clouds; Pleasant",
      "category": "unknown",
      "precip_in": null
    },
    {
      "date": "2026-06-25",
      "day_name": "Thursday",
      "high_f": 78.0,
      "low_f": 60.0,
      "wind_mph": null,
      "wind_lo": null,
      "wind_hi": null,
      "precip_type": "rain",
      "daytime_desc": "Partly sunny; Hit-or-miss afternoon showers & thundershowers",
      "overnight_desc": "Maybe an early shower or thundershower; Partly cloudy",
      "category": "unknown",
      "precip_in": null
    },
    {
      "date": "2026-06-26",
      "day_name": "Friday",
      "high_f": null,
      "low_f": null,
      "wind_mph": null,
      "wind_lo": null,
      "wind_hi": null,
      "precip_type": null,
      "daytime_desc": "",
      "overnight_desc": "",
      "category": "unknown",
      "precip_in": null
    },
    {
      "date": "2026-06-27",
      "day_name": "Saturday",
      "high_f": null,
      "low_f": null,
      "wind_mph": null,
      "wind_lo": null,
      "wind_hi": null,
      "precip_type": "rain",
      "daytime_desc": "Forecast Discussion; Nice weather sticks around for one more day, giving us a great finish to the holiday weekend. A hardly noticeable warm front will push back north through the area today and that will give us a boost in temperatures and some clouds to go along with the sunshine this afternoon.; Clouds and humidity increase tonight ahead of our next summertime cool front. The front brings us rainfall in the form of showers and thunderstorms, which should arrive Monday afternoon and last well into the evening. Rainfall amounts overall don't look tremendous with this next front, but it will help the ongoing drought situation, and we could see a couple of spots wind up with some decent totals. A few showers linger into Tuesday behind the front, mostly along the western escarpment, but these are nothing to write home about and will fade away during the day.; Weak high pressure builds back in for a nicer day Wednesday. This being late June, you know we can't hold dry, stable air off for long. Increasing moisture surges back into the area on Thursday as stubborn high pressure sets up shop over the western Atlantic. This leads to a daily scattering of mostly afternoon and evening showers or thundershowers each day Thursday through Saturday.; Detailed forecast discussion and analysis is only available to RaysWeather supporters.; Log in; Alan Simmons; PHOTO OF THE DAY; CLICK TO ENLARGE; Don\u2019t worry! Just needs to dry off! Submitted by Rebecca McCandless.; All Photos; Submit Photo; Latest Insights; WWR? Wolf Laurel!; <video controls src=\"https://d3efbyumrgw1ny.cloudfront.net/Jun-18-2026-1781795436_0780511.MOV\" width=\"400\"></video>; Jun 18, 2026; Yadkin Valley Deluge; A morning complex of thunderstorms moving across the Ohio Valley and into West Virginia and Virginia produced an outflow boundary that pushed southward into North Carolina during the afternoon of June 18. This outflow boundary, the result of a cool rush of air from thunderstorms occurring to the north, served as an effective focusing mechanism for training thunderstorms that occurred over parts of Surry, northern Wilkes and southern Alleghany County during Thursday afternoon and evening.; This occurred under the backdrop of increasing tropical moisture returning from the southwest as the remnants of Tropical Storm Arthur moved into Alabama.; The result was excessive rainfall, in the range of 2-4 inches, with locally higher amounts of around 5 inches in central Surry County.; Jun 19, 2026; Monday Message for June 15, 2026; It's the pre-summer solstice edition of the Monday Message, available for subscribers. El Ni\u00f1o has officially arrived, and will have significant implications for our weather heading into fall and winter.; Jun 15, 2026; See all; Golf-O-Meter; 0 Golfballs; Only ducks or polar bears.; Good day for knitting.; Maybe, if you are brave.; Worth taking a chance.; A good day to be outside.; Bosses, you'd better stand at the door. (Or will bosses be first out the door?); CONTACT US; Privacy Policy; Terms and Conditions; Contact Us",
      "overnight_desc": "",
      "category": "unknown",
      "precip_in": null
    }
  ],
  "error": null,
  "rebuilt_from": "rays_boone.json",
  "rebuilt_note": "daily[] re-parsed from saved raw_text via fixed capture_rays parsers; dates anchored to capture date; wind interval + precip_type recovered."
}