{
  "source": "metno",
  "label": "Met.no",
  "captured_at": "2026-06-28T11:17:23.408565-04:00",
  "location": "Boone",
  "daily": [
    {
      "date": "2026-06-28",
      "high_f": 73.2,
      "low_f": 65.1,
      "wind_mph": 13.4,
      "precip_type": "rain",
      "rain_in": 0.035,
      "snow_in": null,
      "fields_provided": [
        "high",
        "low",
        "wind",
        "precip_type",
        "rain_amount"
      ]
    },
    {
      "date": "2026-06-29",
      "high_f": 79.5,
      "low_f": 64.8,
      "wind_mph": 9.4,
      "precip_type": "rain",
      "rain_in": 0.035,
      "snow_in": null,
      "fields_provided": [
        "high",
        "low",
        "wind",
        "precip_type",
        "rain_amount"
      ]
    },
    {
      "date": "2026-06-30",
      "high_f": 82.9,
      "low_f": 65.5,
      "wind_mph": 5.6,
      "precip_type": "rain",
      "rain_in": 0.016,
      "snow_in": null,
      "fields_provided": [
        "high",
        "low",
        "wind",
        "precip_type",
        "rain_amount"
      ]
    },
    {
      "date": "2026-07-01",
      "high_f": 84.2,
      "low_f": 69.3,
      "wind_mph": 2.9,
      "precip_type": "rain",
      "rain_in": 0.024,
      "snow_in": null,
      "fields_provided": [
        "high",
        "low",
        "wind",
        "precip_type",
        "rain_amount"
      ]
    },
    {
      "date": "2026-07-02",
      "high_f": 87.4,
      "low_f": 71.1,
      "wind_mph": 6.0,
      "precip_type": "rain",
      "rain_in": 0.016,
      "snow_in": null,
      "fields_provided": [
        "high",
        "low",
        "wind",
        "precip_type",
        "rain_amount"
      ]
    },
    {
      "date": "2026-07-03",
      "high_f": 86.4,
      "low_f": 72.7,
      "wind_mph": 8.1,
      "precip_type": "rain",
      "rain_in": 0.024,
      "snow_in": null,
      "fields_provided": [
        "high",
        "low",
        "wind",
        "precip_type",
        "rain_amount"
      ]
    },
    {
      "date": "2026-07-04",
      "high_f": 84.7,
      "low_f": 65.3,
      "wind_mph": 3.8,
      "precip_type": "rain",
      "rain_in": 0.051,
      "snow_in": null,
      "fields_provided": [
        "high",
        "low",
        "wind",
        "precip_type",
        "rain_amount"
      ]
    },
    {
      "date": "2026-07-05",
      "high_f": 77.2,
      "low_f": 67.1,
      "wind_mph": 3.8,
      "precip_type": "rain",
      "rain_in": 0.087,
      "snow_in": null,
      "fields_provided": [
        "high",
        "low",
        "wind",
        "precip_type",
        "rain_amount"
      ]
    },
    {
      "date": "2026-07-06",
      "high_f": 75.7,
      "low_f": 68.0,
      "wind_mph": 4.0,
      "precip_type": "rain",
      "rain_in": 0.819,
      "snow_in": null,
      "fields_provided": [
        "high",
        "low",
        "wind",
        "precip_type",
        "rain_amount"
      ]
    },
    {
      "date": "2026-07-07",
      "high_f": 75.6,
      "low_f": 66.2,
      "wind_mph": 9.2,
      "precip_type": "rain",
      "rain_in": 0.075,
      "snow_in": null,
      "fields_provided": [
        "high",
        "low",
        "wind",
        "precip_type",
        "rain_amount"
      ]
    },
    {
      "date": "2026-07-08",
      "high_f": 71.1,
      "low_f": 71.1,
      "wind_mph": 9.2,
      "precip_type": "none",
      "rain_in": 0.0,
      "snow_in": null,
      "fields_provided": [
        "high",
        "low",
        "wind",
        "precip_type",
        "rain_amount"
      ]
    }
  ]
}