{
  "date": "2026-05-01",
  "location": "Boone",
  "rows": [
    {
      "source": "openmeteo",
      "lead": 0,
      "score": 95.1,
      "grade": {
        "verdict": "right",
        "ray_count": 5
      },
      "high_err": 2.5,
      "low_err": 0.09999999999999432,
      "high_bias": 2.5,
      "low_bias": 0.09999999999999432
    },
    {
      "source": "openmeteo",
      "lead": 1,
      "score": 92.8,
      "grade": {
        "verdict": "right",
        "ray_count": 5
      },
      "high_err": 3.0,
      "low_err": 1.6000000000000014,
      "high_bias": 3.0,
      "low_bias": -1.6000000000000014
    },
    {
      "source": "openmeteo",
      "lead": 2,
      "score": 97.6,
      "grade": {
        "verdict": "right",
        "ray_count": 5
      },
      "high_err": 1.8999999999999986,
      "low_err": 2.8000000000000043,
      "high_bias": 1.8999999999999986,
      "low_bias": -2.8000000000000043
    },
    {
      "source": "openmeteo",
      "lead": 3,
      "score": 100.0,
      "grade": {
        "verdict": "right",
        "ray_count": 5
      },
      "high_err": 0.10000000000000142,
      "low_err": 0.10000000000000142,
      "high_bias": -0.10000000000000142,
      "low_bias": -0.10000000000000142
    },
    {
      "source": "openmeteo",
      "lead": 4,
      "score": 98.8,
      "grade": {
        "verdict": "right",
        "ray_count": 5
      },
      "high_err": 2.3999999999999986,
      "low_err": 0.8000000000000043,
      "high_bias": 2.3999999999999986,
      "low_bias": -0.8000000000000043
    },
    {
      "source": "openmeteo",
      "lead": 5,
      "score": 72.4,
      "grade": {
        "verdict": "meh",
        "ray_count": 3
      },
      "high_err": 3.3000000000000043,
      "low_err": 3.700000000000003,
      "high_bias": -3.3000000000000043,
      "low_bias": -3.700000000000003
    },
    {
      "source": "raysweather",
      "lead": 0,
      "score": 84.2,
      "grade": {
        "verdict": "right",
        "ray_count": 4
      },
      "high_err": 3.799999999999997,
      "low_err": 0.7000000000000028,
      "high_bias": 3.799999999999997,
      "low_bias": -0.7000000000000028
    },
    {
      "source": "raysweather",
      "lead": 1,
      "score": 87.2,
      "grade": {
        "verdict": "right",
        "ray_count": 4
      },
      "high_err": 2.799999999999997,
      "low_err": 1.7000000000000028,
      "high_bias": 2.799999999999997,
      "low_bias": -1.7000000000000028
    },
    {
      "source": "raysweather",
      "lead": 2,
      "score": 75.2,
      "grade": {
        "verdict": "right",
        "ray_count": 4
      },
      "high_err": 2.799999999999997,
      "low_err": 1.7000000000000028,
      "high_bias": 2.799999999999997,
      "low_bias": -1.7000000000000028
    },
    {
      "source": "raysweather",
      "lead": 3,
      "score": 60.0,
      "grade": {
        "verdict": "meh",
        "ray_count": 3
      },
      "high_err": 1.7999999999999972,
      "low_err": 1.2999999999999972,
      "high_bias": 1.7999999999999972,
      "low_bias": 1.2999999999999972
    },
    {
      "source": "raysweather",
      "lead": 4,
      "score": 80.0,
      "grade": {
        "verdict": "right",
        "ray_count": 4
      },
      "high_err": 0.7999999999999972,
      "low_err": 1.7000000000000028,
      "high_bias": 0.7999999999999972,
      "low_bias": -1.7000000000000028
    }
  ]
}